neva/__init__.py
neva/py.typed
neva/arch/__init__.py
neva/arch/app.py
neva/arch/application.py
neva/arch/config.py
neva/arch/facade.py
neva/arch/service_provider.py
neva/config/__init__.py
neva/config/base_providers.py
neva/config/loader.py
neva/config/provider.py
neva/config/repository.py
neva/database/__init__.py
neva/database/config.py
neva/database/manager.py
neva/database/provider.py
neva/database/repository.py
neva/events/__init__.py
neva/events/dispatcher.py
neva/events/event.py
neva/events/event_registry.py
neva/events/interface.py
neva/events/listener.py
neva/obs/__init__.py
neva/obs/logging/__init__.py
neva/obs/logging/manager.py
neva/obs/logging/provider.py
neva/obs/middleware/__init__.py
neva/obs/middleware/correlation.py
neva/obs/middleware/profiler.py
neva/support/__init__.py
neva/support/accessors.py
neva/support/results.py
neva/support/strconv.py
neva/support/time.py
neva/support/facade/__init__.py
neva/support/facade/app.py
neva/support/facade/app.pyi
neva/support/facade/config.py
neva/support/facade/config.pyi
neva/support/facade/log.py
neva/support/facade/log.pyi
python_neva-0.2.2.dist-info/METADATA
python_neva-0.2.2.dist-info/WHEEL
python_neva-0.2.2.dist-info/RECORD
