Metadata-Version: 2.4
Name: python-neva
Version: 0.2.2
Summary: Add your description here
Requires-Python: >=3.12
Requires-Dist: dependency-injector>=4.48.3
Requires-Dist: dishka>=1.7.2
Requires-Dist: fastapi-cli>=0.0.16
Requires-Dist: fastapi[all]>=0.124.0
Requires-Dist: pyinstrument>=5.1.1
Requires-Dist: structlog>=25.5.0
Requires-Dist: tortoise-orm[accel]>=0.25.3
